mkdocs_zip_folders-1.0.5.dist-info/licenses/LICENSE
zip_folders/__init__.py
zip_folders/plugin.py
mkdocs_zip_folders-1.0.5.dist-info/METADATA
mkdocs_zip_folders-1.0.5.dist-info/WHEEL
mkdocs_zip_folders-1.0.5.dist-info/entry_points.txt
mkdocs_zip_folders-1.0.5.dist-info/top_level.txt
mkdocs_zip_folders-1.0.5.dist-info/RECORD
