Metadata-Version: 2.4
Name: mkdocs-zip-folders
Version: 1.0.5
Summary: MkDocs plugin to zip configured folders and add them to the site.
Home-page: https://github.com/JakubAndrysek/mkdocs-zip-folders
Author: Jakub Andrýsek
Author-email: email@kubaandrysek.cz
License: MIT
Project-URL: Source, https://github.com/JakubAndrysek/mkdocs-zip-folders
Project-URL: Documentation, https://zip-folders.kubaandrysek.cz/
Project-URL: Tracker, https://github.com/JakubAndrysek/mkdocs-zip-folders/issues
Project-URL: Funding, https://github.com/sponsors/jakubandrysek
Keywords: mkdocs plugin zip folders download zip-folders
Classifier: License :: OSI Approved :: MIT License
Classifier: Programming Language :: Python :: 3.7
Classifier: Programming Language :: Python :: 3.8
Classifier: Programming Language :: Python :: 3.9
Classifier: Programming Language :: Python :: 3.10
Classifier: Programming Language :: Python :: 3.11
Classifier: Programming Language :: Python :: 3.12
Classifier: Programming Language :: Python :: 3.13
Classifier: Operating System :: OS Independent
Requires-Python: >=3.7
License-File: LICENSE
Requires-Dist: mkdocs
Provides-Extra: dev
Requires-Dist: mkdocs-material; extra == "dev"
Requires-Dist: mkdocs-open-in-new-tab; extra == "dev"
Requires-Dist: mkdocs-glightbox; extra == "dev"
Requires-Dist: mkdocs-git-revision-date-localized-plugin; extra == "dev"
Requires-Dist: setuptools; extra == "dev"
Requires-Dist: build; extra == "dev"
Requires-Dist: twine; extra == "dev"
Dynamic: description
Dynamic: description-content-type
Dynamic: license-file
